phpipam_client/__init__.py
phpipam_client/client.py
phpipam_client/rijndael.py
phpipam_client-0.4.0.dist-info/LICENSE
phpipam_client-0.4.0.dist-info/WHEEL
phpipam_client-0.4.0.dist-info/METADATA
phpipam_client-0.4.0.dist-info/RECORD
