Metadata-Version: 2.1
Name: phpipam-client
Version: 0.4.0
Summary: PHPIPAM Python RESP API Client
Home-page: https://github.com/adzhurinskij/phpipam-client
License: MIT
Author: Alexandr Dzhurinskij
Author-email: adzhurinskij@gmail.com
Requires-Python: >=2.7, !=3.0.*, !=3.1.*, !=3.2.*, !=3.3.*
Classifier: License :: OSI Approved :: MIT License
Classifier: Programming Language :: Python :: 2
Classifier: Programming Language :: Python :: 2.7
Classifier: Programming Language :: Python :: 3
Classifier: Programming Language :: Python :: 3.4
Classifier: Programming Language :: Python :: 3.5
Classifier: Programming Language :: Python :: 3.6
Classifier: Programming Language :: Python :: 3.7
Classifier: Programming Language :: Python :: 3.8
Requires-Dist: requests (>=2.21,<3.0)
